picklachu/__init__.py
picklachu/picklachu.py
test/__init__.py
test/test_local.py
test/test_picklachu.py
picklachu-0.0.3.dist-info/LICENSE
picklachu-0.0.3.dist-info/METADATA
picklachu-0.0.3.dist-info/WHEEL
picklachu-0.0.3.dist-info/top_level.txt
picklachu-0.0.3.dist-info/RECORD
