Metadata-Version: 2.1
Name: picklachu
Version: 0.0.3
Summary: Pickle data an store it
Home-page: https://github.com/fowbi/picklachu
Author: tobinho
Author-email: tobi@magier.be
License: UNKNOWN
Platform: UNKNOWN
Classifier: Programming Language :: Python :: 3
Classifier: License :: OSI Approved :: MIT License
Classifier: Operating System :: OS Independent
